kiwis_pie/__init__.py
kiwis_pie/_version.py
kiwis_pie/kiwis.py
kiwis_pie-0.10.1.dist-info/LICENSE
kiwis_pie-0.10.1.dist-info/METADATA
kiwis_pie-0.10.1.dist-info/WHEEL
kiwis_pie-0.10.1.dist-info/top_level.txt
kiwis_pie-0.10.1.dist-info/RECORD
